the_count_of_words/__init__.py
the_count_of_words/the_count_of_words.py
the_count_of_words-0.0.6.dist-info/LICENSE
the_count_of_words-0.0.6.dist-info/METADATA
the_count_of_words-0.0.6.dist-info/WHEEL
the_count_of_words-0.0.6.dist-info/top_level.txt
the_count_of_words-0.0.6.dist-info/RECORD
