Metadata-Version: 2.1
Name: the-count-of-words
Version: 0.0.6
Summary: Words counter
Home-page: https://github.com/RavidEliyahu/the-count-of-words
Author: Ravid Eliyahu
Author-email: ravid1233@gmail.com
License: MIT
Platform: UNKNOWN
Classifier: Programming Language :: Python :: 3
Classifier: License :: OSI Approved :: MIT License
Classifier: Operating System :: OS Independent
